<?xml version="1.0" encoding="UTF-8"?><quotes languages="el|eo|en|zh|af|vi|ca|it|cs|cy|ar|eu|et|az|id|es|ru|gl|nl|pt|no|tr|li|lt|th|te|is|pl|be|fr|bg|uk|sl|hr|de|da|fa|bs|fi|hy|hu|ja|he|ka|sr|sq|ko|sv|sk|ku|mr"><quote id="0" author="Mark Twain" cats="Người Mỹ|Nhà diễn thuyết|Nhà văn|Tiểu thuyết gia" ref="">"Bất kỳ sự tổng quát hóa nào, đều là sai, tính cả cái này."</quote><quote id="1" author="Mark Twain" cats="Người Mỹ|Nhà diễn thuyết|Nhà văn|Tiểu thuyết gia" ref="">"Hãy tìm các lý lẽ trước, sau đó bạn có thể vui vẻ mà vặn vẹo họ chừng nào bạn muốn."</quote><quote id="2" author="Mark Twain" cats="Người Mỹ|Nhà diễn thuyết|Nhà văn|Tiểu thuyết gia" ref="">"Sự khác nhau giữa một từ đúng và một từ gần đúng cũng giống như sự khác nhau giữa sấm chớp và một con đom đóm."</quote><quote id="3" author="Mark Twain" cats="Người Mỹ|Nhà diễn thuyết|Nhà văn|Tiểu thuyết gia" ref="">Càng cấm một thứ, thứ đó càng trở nên phổ biến.</quote><quote id="4" author="Mark Twain" cats="Người Mỹ|Nhà diễn thuyết|Nhà văn|Tiểu thuyết gia" ref="">Bạn càng giải thích thì tôi càng không hiểu.</quote><quote id="5" author="Mark Twain" cats="Người Mỹ|Nhà diễn thuyết|Nhà văn|Tiểu thuyết gia" ref="">Có hai nhóm người: một nhóm thì hoàn thành các công việc còn nhóm kia tuyên bố rằng họ đã hoàn thành các công việc. Nhóm thứ nhất thì ít đông đúc hơn nhóm kia.</quote></quotes>